{
  "timestamp": "2025-08-17T04:19:29.816Z",
  "baselines": {
    "workflow": {
      "totalWorkflows": 0,
      "activeWorkflows": 0,
      "workflowsWithIssues": 0,
      "totalIssues": 0,
      "successRate": 100
    },
    "resource": {
      "memoryUsage": {
        "rss": 30224384,
        "heapUsed": 4570344,
        "heapTotal": 5574656,
        "external": 1562113
      },
      "cpuUsage": {
        "user": 99715,
        "system": 2712,
        "percentage": 102.427
      },
      "diskUsage": {
        "automationDirSize": 2309258,
        "availableSpace": "unknown",
        "usagePercentage": "unknown"
      },
      "networkLatency": {
        "latency": 0,
        "status": "local",
        "timestamp": "2025-08-17T04:19:23.290Z"
      }
    },
    "system": {
      "responseTime": 423,
      "systemLoad": {
        "loadAverage": "unknown",
        "processCount": 73053,
        "timestamp": "2025-08-17T04:19:23.714Z"
      },
      "uptime": {
        "processUptime": 0.986559611,
        "timestamp": "2025-08-17T04:19:23.714Z"
      },
      "timestamp": "2025-08-17T04:19:23.714Z"
    },
    "timestamp": "2025-08-17T04:19:23.714Z"
  },
  "optimizations": [
    {
      "success": true,
      "optimizations": [
        "file_caching_optimization",
        "memory_pool_optimization"
      ],
      "message": "Applied 2 memory optimizations",
      "type": "memory_optimization",
      "timestamp": "2025-08-17T04:19:23.717Z",
      "opportunity": {
        "type": "memory_optimization",
        "priority": "medium",
        "description": "Optimize memory usage and reduce heap consumption",
        "estimatedImpact": "10-20% improvement",
        "effort": "low",
        "strategies": [
          "garbage_collection",
          "memory_pooling",
          "cache_optimization"
        ]
      }
    },
    {
      "success": true,
      "optimizations": [
        "code_optimization",
        "configuration_optimization",
        "monitoring_optimization"
      ],
      "message": "Applied 3 general optimizations",
      "type": "general_optimization",
      "timestamp": "2025-08-17T04:19:23.717Z",
      "opportunity": {
        "type": "general_optimization",
        "priority": "low",
        "description": "Apply general performance improvements",
        "estimatedImpact": "5-15% improvement",
        "effort": "low",
        "strategies": [
          "code_optimization",
          "configuration_tuning",
          "monitoring_improvement"
        ]
      }
    }
  ],
  "validation": [
    {
      "type": "memory_optimization",
      "validated": true,
      "improvement": 0,
      "shouldKeep": false,
      "afterPerformance": {
        "workflow": {
          "totalWorkflows": 0,
          "activeWorkflows": 0,
          "workflowsWithIssues": 0,
          "totalIssues": 0,
          "successRate": 100
        },
        "resource": {
          "memoryUsage": {
            "rss": 38019072,
            "heapUsed": 4906744,
            "heapTotal": 7147520,
            "external": 1569651
          },
          "cpuUsage": {
            "user": 99194,
            "system": 324,
            "percentage": 99.518
          },
          "diskUsage": {
            "automationDirSize": 2309258,
            "availableSpace": "unknown",
            "usagePercentage": "unknown"
          },
          "networkLatency": {
            "latency": 0,
            "status": "local",
            "timestamp": "2025-08-17T04:19:26.444Z"
          }
        },
        "system": {
          "responseTime": 425,
          "systemLoad": {
            "loadAverage": "unknown",
            "processCount": 73053,
            "timestamp": "2025-08-17T04:19:26.869Z"
          },
          "uptime": {
            "processUptime": 4.141696994,
            "timestamp": "2025-08-17T04:19:26.869Z"
          },
          "timestamp": "2025-08-17T04:19:26.869Z"
        },
        "timestamp": "2025-08-17T04:19:26.869Z"
      },
      "timestamp": "2025-08-17T04:19:26.869Z"
    },
    {
      "type": "general_optimization",
      "validated": true,
      "improvement": 0.05,
      "shouldKeep": false,
      "afterPerformance": {
        "workflow": {
          "totalWorkflows": 0,
          "activeWorkflows": 0,
          "workflowsWithIssues": 0,
          "totalIssues": 0,
          "successRate": 100
        },
        "resource": {
          "memoryUsage": {
            "rss": 38129664,
            "heapUsed": 5046704,
            "heapTotal": 7147520,
            "external": 1569651
          },
          "cpuUsage": {
            "user": 98828,
            "system": 299,
            "percentage": 99.127
          },
          "diskUsage": {
            "automationDirSize": 2309258,
            "availableSpace": "unknown",
            "usagePercentage": "unknown"
          },
          "networkLatency": {
            "latency": 0,
            "status": "local",
            "timestamp": "2025-08-17T04:19:29.396Z"
          }
        },
        "system": {
          "responseTime": 419,
          "systemLoad": {
            "loadAverage": "unknown",
            "processCount": 73053,
            "timestamp": "2025-08-17T04:19:29.815Z"
          },
          "uptime": {
            "processUptime": 7.087673414,
            "timestamp": "2025-08-17T04:19:29.815Z"
          },
          "timestamp": "2025-08-17T04:19:29.815Z"
        },
        "timestamp": "2025-08-17T04:19:29.815Z"
      },
      "timestamp": "2025-08-17T04:19:29.815Z"
    }
  ],
  "summary": {
    "totalOptimizations": 2,
    "successfulOptimizations": 2,
    "validatedOptimizations": 2,
    "keptOptimizations": 0,
    "averageImprovement": 2.5,
    "successRate": 100,
    "validationRate": 100
  },
  "recommendations": [
    {
      "priority": "medium",
      "action": "Review low-impact optimizations",
      "description": "2 optimizations showed minimal improvement",
      "impact": "medium"
    },
    {
      "priority": "low",
      "action": "Monitor optimization performance",
      "description": "Continue monitoring to ensure optimizations remain effective",
      "impact": "low"
    }
  ]
}