{
  "timestamp": "2025-08-17T01:22:36.450Z",
  "baselines": {
    "workflow": {
      "totalWorkflows": 0,
      "activeWorkflows": 0,
      "workflowsWithIssues": 0,
      "totalIssues": 0,
      "successRate": 100
    },
    "resource": {
      "memoryUsage": {
        "rss": 30326784,
        "heapUsed": 4570344,
        "heapTotal": 5574656,
        "external": 1562113
      },
      "cpuUsage": {
        "user": 100656,
        "system": 2216,
        "percentage": 102.87200000000001
      },
      "diskUsage": {
        "automationDirSize": 2309258,
        "availableSpace": "unknown",
        "usagePercentage": "unknown"
      },
      "networkLatency": {
        "latency": 0,
        "status": "local",
        "timestamp": "2025-08-17T01:22:30.085Z"
      }
    },
    "system": {
      "responseTime": 422,
      "systemLoad": {
        "loadAverage": "unknown",
        "processCount": 61614,
        "timestamp": "2025-08-17T01:22:30.509Z"
      },
      "uptime": {
        "processUptime": 0.979396612,
        "timestamp": "2025-08-17T01:22:30.509Z"
      },
      "timestamp": "2025-08-17T01:22:30.509Z"
    },
    "timestamp": "2025-08-17T01:22:30.509Z"
  },
  "optimizations": [
    {
      "success": true,
      "optimizations": [
        "file_caching_optimization",
        "memory_pool_optimization"
      ],
      "message": "Applied 2 memory optimizations",
      "type": "memory_optimization",
      "timestamp": "2025-08-17T01:22:30.512Z",
      "opportunity": {
        "type": "memory_optimization",
        "priority": "medium",
        "description": "Optimize memory usage and reduce heap consumption",
        "estimatedImpact": "10-20% improvement",
        "effort": "low",
        "strategies": [
          "garbage_collection",
          "memory_pooling",
          "cache_optimization"
        ]
      }
    },
    {
      "success": true,
      "optimizations": [
        "code_optimization",
        "configuration_optimization",
        "monitoring_optimization"
      ],
      "message": "Applied 3 general optimizations",
      "type": "general_optimization",
      "timestamp": "2025-08-17T01:22:30.512Z",
      "opportunity": {
        "type": "general_optimization",
        "priority": "low",
        "description": "Apply general performance improvements",
        "estimatedImpact": "5-15% improvement",
        "effort": "low",
        "strategies": [
          "code_optimization",
          "configuration_tuning",
          "monitoring_improvement"
        ]
      }
    }
  ],
  "validation": [
    {
      "type": "memory_optimization",
      "validated": true,
      "improvement": 0.026221220984678616,
      "shouldKeep": false,
      "afterPerformance": {
        "workflow": {
          "totalWorkflows": 0,
          "activeWorkflows": 0,
          "workflowsWithIssues": 0,
          "totalIssues": 0,
          "successRate": 100
        },
        "resource": {
          "memoryUsage": {
            "rss": 38105088,
            "heapUsed": 4450504,
            "heapTotal": 7147520,
            "external": 1562169
          },
          "cpuUsage": {
            "user": 98141,
            "system": 492,
            "percentage": 98.633
          },
          "diskUsage": {
            "automationDirSize": 2309258,
            "availableSpace": "unknown",
            "usagePercentage": "unknown"
          },
          "networkLatency": {
            "latency": 0,
            "status": "local",
            "timestamp": "2025-08-17T01:22:33.060Z"
          }
        },
        "system": {
          "responseTime": 427,
          "systemLoad": {
            "loadAverage": "unknown",
            "processCount": 61614,
            "timestamp": "2025-08-17T01:22:33.487Z"
          },
          "uptime": {
            "processUptime": 3.957190271,
            "timestamp": "2025-08-17T01:22:33.487Z"
          },
          "timestamp": "2025-08-17T01:22:33.487Z"
        },
        "timestamp": "2025-08-17T01:22:33.487Z"
      },
      "timestamp": "2025-08-17T01:22:33.487Z"
    },
    {
      "type": "general_optimization",
      "validated": true,
      "improvement": 0.05,
      "shouldKeep": false,
      "afterPerformance": {
        "workflow": {
          "totalWorkflows": 0,
          "activeWorkflows": 0,
          "workflowsWithIssues": 0,
          "totalIssues": 0,
          "successRate": 100
        },
        "resource": {
          "memoryUsage": {
            "rss": 38518784,
            "heapUsed": 4456664,
            "heapTotal": 7147520,
            "external": 1562169
          },
          "cpuUsage": {
            "user": 98430,
            "system": 808,
            "percentage": 99.238
          },
          "diskUsage": {
            "automationDirSize": 2309258,
            "availableSpace": "unknown",
            "usagePercentage": "unknown"
          },
          "networkLatency": {
            "latency": 0,
            "status": "local",
            "timestamp": "2025-08-17T01:22:36.026Z"
          }
        },
        "system": {
          "responseTime": 423,
          "systemLoad": {
            "loadAverage": "unknown",
            "processCount": 61614,
            "timestamp": "2025-08-17T01:22:36.449Z"
          },
          "uptime": {
            "processUptime": 6.919513216,
            "timestamp": "2025-08-17T01:22:36.449Z"
          },
          "timestamp": "2025-08-17T01:22:36.449Z"
        },
        "timestamp": "2025-08-17T01:22:36.449Z"
      },
      "timestamp": "2025-08-17T01:22:36.449Z"
    }
  ],
  "summary": {
    "totalOptimizations": 2,
    "successfulOptimizations": 2,
    "validatedOptimizations": 2,
    "keptOptimizations": 0,
    "averageImprovement": 3.811061049233931,
    "successRate": 100,
    "validationRate": 100
  },
  "recommendations": [
    {
      "priority": "medium",
      "action": "Review low-impact optimizations",
      "description": "2 optimizations showed minimal improvement",
      "impact": "medium"
    },
    {
      "priority": "low",
      "action": "Monitor optimization performance",
      "description": "Continue monitoring to ensure optimizations remain effective",
      "impact": "low"
    }
  ]
}