{
  "timestamp": "2025-08-17T18:47:35.773Z",
  "baselines": {
    "workflow": {
      "totalWorkflows": 0,
      "activeWorkflows": 0,
      "workflowsWithIssues": 0,
      "totalIssues": 0,
      "successRate": 100
    },
    "resource": {
      "memoryUsage": {
        "rss": 30568448,
        "heapUsed": 4570352,
        "heapTotal": 5574656,
        "external": 1568670
      },
      "cpuUsage": {
        "user": 100133,
        "system": 2431,
        "percentage": 102.564
      },
      "diskUsage": {
        "automationDirSize": 2309258,
        "availableSpace": "unknown",
        "usagePercentage": "unknown"
      },
      "networkLatency": {
        "latency": 0,
        "status": "local",
        "timestamp": "2025-08-17T18:47:28.258Z"
      }
    },
    "system": {
      "responseTime": 455,
      "systemLoad": {
        "loadAverage": "unknown",
        "processCount": 32849,
        "timestamp": "2025-08-17T18:47:28.714Z"
      },
      "uptime": {
        "processUptime": 1.075591838,
        "timestamp": "2025-08-17T18:47:28.715Z"
      },
      "timestamp": "2025-08-17T18:47:28.715Z"
    },
    "timestamp": "2025-08-17T18:47:28.715Z"
  },
  "optimizations": [
    {
      "success": true,
      "optimizations": [
        "file_caching_optimization",
        "memory_pool_optimization"
      ],
      "message": "Applied 2 memory optimizations",
      "type": "memory_optimization",
      "timestamp": "2025-08-17T18:47:28.717Z",
      "opportunity": {
        "type": "memory_optimization",
        "priority": "medium",
        "description": "Optimize memory usage and reduce heap consumption",
        "estimatedImpact": "10-20% improvement",
        "effort": "low",
        "strategies": [
          "garbage_collection",
          "memory_pooling",
          "cache_optimization"
        ]
      }
    },
    {
      "success": true,
      "optimizations": [
        "code_optimization",
        "configuration_optimization",
        "monitoring_optimization"
      ],
      "message": "Applied 3 general optimizations",
      "type": "general_optimization",
      "timestamp": "2025-08-17T18:47:28.717Z",
      "opportunity": {
        "type": "general_optimization",
        "priority": "low",
        "description": "Apply general performance improvements",
        "estimatedImpact": "5-15% improvement",
        "effort": "low",
        "strategies": [
          "code_optimization",
          "configuration_tuning",
          "monitoring_improvement"
        ]
      }
    }
  ],
  "validation": [
    {
      "type": "memory_optimization",
      "validated": true,
      "improvement": 0,
      "shouldKeep": false,
      "afterPerformance": {
        "workflow": {
          "totalWorkflows": 0,
          "activeWorkflows": 0,
          "workflowsWithIssues": 0,
          "totalIssues": 0,
          "successRate": 100
        },
        "resource": {
          "memoryUsage": {
            "rss": 38043648,
            "heapUsed": 4985632,
            "heapTotal": 7147520,
            "external": 1582765
          },
          "cpuUsage": {
            "user": 93913,
            "system": 1319,
            "percentage": 95.232
          },
          "diskUsage": {
            "automationDirSize": 2309258,
            "availableSpace": "unknown",
            "usagePercentage": "unknown"
          },
          "networkLatency": {
            "latency": 0,
            "status": "local",
            "timestamp": "2025-08-17T18:47:31.793Z"
          }
        },
        "system": {
          "responseTime": 699,
          "systemLoad": {
            "loadAverage": "unknown",
            "processCount": 32849,
            "timestamp": "2025-08-17T18:47:32.492Z"
          },
          "uptime": {
            "processUptime": 4.853270313,
            "timestamp": "2025-08-17T18:47:32.492Z"
          },
          "timestamp": "2025-08-17T18:47:32.492Z"
        },
        "timestamp": "2025-08-17T18:47:32.492Z"
      },
      "timestamp": "2025-08-17T18:47:32.492Z"
    },
    {
      "type": "general_optimization",
      "validated": true,
      "improvement": 0.05,
      "shouldKeep": false,
      "afterPerformance": {
        "workflow": {
          "totalWorkflows": 0,
          "activeWorkflows": 0,
          "workflowsWithIssues": 0,
          "totalIssues": 0,
          "successRate": 100
        },
        "resource": {
          "memoryUsage": {
            "rss": 38342656,
            "heapUsed": 5255120,
            "heapTotal": 7147520,
            "external": 1582765
          },
          "cpuUsage": {
            "user": 89035,
            "system": 1394,
            "percentage": 90.429
          },
          "diskUsage": {
            "automationDirSize": 2309258,
            "availableSpace": "unknown",
            "usagePercentage": "unknown"
          },
          "networkLatency": {
            "latency": 0,
            "status": "local",
            "timestamp": "2025-08-17T18:47:35.308Z"
          }
        },
        "system": {
          "responseTime": 464,
          "systemLoad": {
            "loadAverage": "unknown",
            "processCount": 32849,
            "timestamp": "2025-08-17T18:47:35.772Z"
          },
          "uptime": {
            "processUptime": 8.133473297,
            "timestamp": "2025-08-17T18:47:35.772Z"
          },
          "timestamp": "2025-08-17T18:47:35.772Z"
        },
        "timestamp": "2025-08-17T18:47:35.772Z"
      },
      "timestamp": "2025-08-17T18:47:35.772Z"
    }
  ],
  "summary": {
    "totalOptimizations": 2,
    "successfulOptimizations": 2,
    "validatedOptimizations": 2,
    "keptOptimizations": 0,
    "averageImprovement": 2.5,
    "successRate": 100,
    "validationRate": 100
  },
  "recommendations": [
    {
      "priority": "medium",
      "action": "Review low-impact optimizations",
      "description": "2 optimizations showed minimal improvement",
      "impact": "medium"
    },
    {
      "priority": "low",
      "action": "Monitor optimization performance",
      "description": "Continue monitoring to ensure optimizations remain effective",
      "impact": "low"
    }
  ]
}