{
  "generatedAt": "2025-08-13T22:20:28.334Z",
  "items": [
    {
      "title": "Guide — Reports Trends Implementation",
      "href": "/reports/guides/guide-2025-08-13-222028",
      "desc": "New autonomous content",
      "createdAt": "2025-08-13T22:20:28.260Z",
      "source": "cloud-deep-research-factory"
    },
    {
      "title": "Pattern — Cloud Improving Continuously",
      "href": "/reports/patterns/pattern-2025-08-13-222028",
      "desc": "New autonomous content",
      "createdAt": "2025-08-13T22:20:28.260Z",
      "source": "cloud-deep-research-factory"
    },
    {
      "title": "Guide — Reports Trends Implementation",
      "href": "/reports/guides/guide-2025-08-13-222010",
      "desc": "New autonomous content",
      "createdAt": "2025-08-13T22:20:10.901Z",
      "source": "cloud-deep-research-factory"
    },
    {
      "title": "Pattern — Cloud Improving Continuously",
      "href": "/reports/patterns/pattern-2025-08-13-222010",
      "desc": "New autonomous content",
      "createdAt": "2025-08-13T22:20:10.901Z",
      "source": "cloud-deep-research-factory"
    },
    {
      "title": "Innovation Insight — 2025-08-13 22-20",
      "href": "/reports/innovations/insight-2025-08-13T22-20",
      "desc": "New autonomous content",
      "createdAt": "2025-08-13T22:20:10.815Z",
      "source": "cloud-content-factory"
    },
    {
      "title": "Autonomous Update — 2025-08-13 22-20",
      "href": "/reports/updates/update-2025-08-13T22-20",
      "desc": "New autonomous content",
      "createdAt": "2025-08-13T22:20:10.815Z",
      "source": "cloud-content-factory"
    },
    {
      "title": "Innovation Insight — 2025-08-13 22-20",
      "href": "/reports/innovations/insight-2025-08-13T22-20",
      "desc": "New autonomous content",
      "createdAt": "2025-08-13T22:20:10.653Z",
      "source": "cloud-content-factory"
    },
    {
      "title": "Autonomous Update — 2025-08-13 22-20",
      "href": "/reports/updates/update-2025-08-13T22-20",
      "desc": "New autonomous content",
      "createdAt": "2025-08-13T22:20:10.653Z",
      "source": "cloud-content-factory"
    },
    {
      "id": "cursor-chat-2025-08-13T22:20:10.980Z",
      "type": "cursor-chat",
      "timestamp": "2025-08-13T22:20:10.980Z"
    }
  ]
}